README.md
setup.cfg
setup.py
gokg_distributions/Binomialdistribution.py
gokg_distributions/Gaussiandistribution.py
gokg_distributions/Generaldistribution.py
gokg_distributions/__init__.py
gokg_distributions.egg-info/PKG-INFO
gokg_distributions.egg-info/SOURCES.txt
gokg_distributions.egg-info/dependency_links.txt
gokg_distributions.egg-info/not-zip-safe
gokg_distributions.egg-info/top_level.txt